fardoes/__init__.py
fardoes/__main__.py
fardoes/cli.py
fardoes-0.1.0.dist-info/METADATA
fardoes-0.1.0.dist-info/WHEEL
fardoes-0.1.0.dist-info/entry_points.txt
fardoes-0.1.0.dist-info/RECORD
