Metadata-Version: 2.3
Name: fardoes
Version: 0.1.0
Summary: Add your description here
Author-email: Taylor Monacelli <taylormonacelli@gmail.com>
Requires-Python: >=3.8
Requires-Dist: jinja2>=3.1.3
Requires-Dist: matplotlib>=3.7.5
Requires-Dist: numpy>=1.24.4
